{
"meta":{"test_sets":[],"test_metrics":[],"learn_metrics":[{"best_value":"Min","name":"RMSE"}],"launch_mode":"Train","parameters":"","iteration_count":100,"learn_sets":["learn"],"name":"experiment"},
"iterations":[
{"learn":[14.53867225],"iteration":0,"passed_time":0.1567216905,"remaining_time":15.51544736},
{"learn":[14.10897893],"iteration":1,"passed_time":0.1618297648,"remaining_time":7.929658473},
{"learn":[13.63714331],"iteration":2,"passed_time":0.1662244573,"remaining_time":5.374590786},
{"learn":[13.20431305],"iteration":3,"passed_time":0.1729928442,"remaining_time":4.151828261},
{"learn":[12.82809491],"iteration":4,"passed_time":0.1775092216,"remaining_time":3.37267521},
{"learn":[12.4771186],"iteration":5,"passed_time":0.1816752409,"remaining_time":2.846245441},
{"learn":[12.11807366],"iteration":6,"passed_time":0.1847679526,"remaining_time":2.454774227},
{"learn":[11.78386607],"iteration":7,"passed_time":0.1886317099,"remaining_time":2.169264664},
{"learn":[11.44732521],"iteration":8,"passed_time":0.1928681643,"remaining_time":1.950111439},
{"learn":[11.11431051],"iteration":9,"passed_time":0.1969216201,"remaining_time":1.772294581},
{"learn":[10.83006828],"iteration":10,"passed_time":0.1994488025,"remaining_time":1.613722129},
{"learn":[10.52995306],"iteration":11,"passed_time":0.2036865121,"remaining_time":1.493701089},
{"learn":[10.27013125],"iteration":12,"passed_time":0.2079706385,"remaining_time":1.391803504},
{"learn":[10.01665732],"iteration":13,"passed_time":0.2101531314,"remaining_time":1.290940664},
{"learn":[9.764617027],"iteration":14,"passed_time":0.2139591289,"remaining_time":1.212435064},
{"learn":[9.534515512],"iteration":15,"passed_time":0.2177359729,"remaining_time":1.143113858},
{"learn":[9.316997283],"iteration":16,"passed_time":0.2213636732,"remaining_time":1.080775581},
{"learn":[9.100325035],"iteration":17,"passed_time":0.2264243142,"remaining_time":1.031488543},
{"learn":[8.88760238],"iteration":18,"passed_time":0.2313128062,"remaining_time":0.9861230159},
{"learn":[8.681113715],"iteration":19,"passed_time":0.2356849674,"remaining_time":0.9427398697},
{"learn":[8.49326332],"iteration":20,"passed_time":0.2394915079,"remaining_time":0.9009442439},
{"learn":[8.323962683],"iteration":21,"passed_time":0.2437280686,"remaining_time":0.8641267887},
{"learn":[8.141158105],"iteration":22,"passed_time":0.2479726603,"remaining_time":0.8301693411},
{"learn":[7.9879774],"iteration":23,"passed_time":0.2520143476,"remaining_time":0.7980454342},
{"learn":[7.841502618],"iteration":24,"passed_time":0.2562934887,"remaining_time":0.7688804661},
{"learn":[7.683229474],"iteration":25,"passed_time":0.2606286335,"remaining_time":0.7417891878},
{"learn":[7.544598303],"iteration":26,"passed_time":0.2650137426,"remaining_time":0.7165186373},
{"learn":[7.41174181],"iteration":27,"passed_time":0.2692070355,"remaining_time":0.6922466626},
{"learn":[7.2853234],"iteration":28,"passed_time":0.273106386,"remaining_time":0.6686397726},
{"learn":[7.180984169],"iteration":29,"passed_time":0.2773306023,"remaining_time":0.6471047387},
{"learn":[7.063490103],"iteration":30,"passed_time":0.279692079,"remaining_time":0.6225404338},
{"learn":[6.953575088],"iteration":31,"passed_time":0.2837476832,"remaining_time":0.6029638269},
{"learn":[6.852980141],"iteration":32,"passed_time":0.2874847409,"remaining_time":0.5836811405},
{"learn":[6.773896171],"iteration":33,"passed_time":0.2918483559,"remaining_time":0.5665291615},
{"learn":[6.684013755],"iteration":34,"passed_time":0.2961494037,"remaining_time":0.5499917497},
{"learn":[6.593824525],"iteration":35,"passed_time":0.300259437,"remaining_time":0.5337945548},
{"learn":[6.519308227],"iteration":36,"passed_time":0.3042701315,"remaining_time":0.5180815753},
{"learn":[6.444841255],"iteration":37,"passed_time":0.3096616024,"remaining_time":0.5052373512},
{"learn":[6.364417446],"iteration":38,"passed_time":0.3139513877,"remaining_time":0.4910521706},
{"learn":[6.299736861],"iteration":39,"passed_time":0.3179632853,"remaining_time":0.476944928},
{"learn":[6.227474448],"iteration":40,"passed_time":0.3220531056,"remaining_time":0.4634422739},
{"learn":[6.166973788],"iteration":41,"passed_time":0.3267432839,"remaining_time":0.4512169159},
{"learn":[6.105129567],"iteration":42,"passed_time":0.3311652435,"remaining_time":0.4389864856},
{"learn":[6.044776445],"iteration":43,"passed_time":0.3385828819,"remaining_time":0.4309236679},
{"learn":[5.98789923],"iteration":44,"passed_time":0.3430243702,"remaining_time":0.419252008},
{"learn":[5.93705109],"iteration":45,"passed_time":0.3473171738,"remaining_time":0.4077201606},
{"learn":[5.883662442],"iteration":46,"passed_time":0.3513397401,"remaining_time":0.3961916218},
{"learn":[5.833859799],"iteration":47,"passed_time":0.3556593915,"remaining_time":0.3852976742},
{"learn":[5.785133358],"iteration":48,"passed_time":0.3601359517,"remaining_time":0.3748353783},
{"learn":[5.742048727],"iteration":49,"passed_time":0.3643099469,"remaining_time":0.3643099469},
{"learn":[5.707158179],"iteration":50,"passed_time":0.3690620645,"remaining_time":0.3545890423},
{"learn":[5.66419556],"iteration":51,"passed_time":0.3732810424,"remaining_time":0.344567116},
{"learn":[5.624810946],"iteration":52,"passed_time":0.3778341475,"remaining_time":0.3350604704},
{"learn":[5.59023988],"iteration":53,"passed_time":0.383444458,"remaining_time":0.3266378716},
{"learn":[5.554354726],"iteration":54,"passed_time":0.3885851688,"remaining_time":0.31793332},
{"learn":[5.522794985],"iteration":55,"passed_time":0.3944922681,"remaining_time":0.3099582107},
{"learn":[5.490980971],"iteration":56,"passed_time":0.3990129034,"remaining_time":0.3010097342},
{"learn":[5.460813023],"iteration":57,"passed_time":0.4034216171,"remaining_time":0.2921328951},
{"learn":[5.435830717],"iteration":58,"passed_time":0.4085809871,"remaining_time":0.2839291605},
{"learn":[5.40781387],"iteration":59,"passed_time":0.4128407606,"remaining_time":0.2752271737},
{"learn":[5.380330516],"iteration":60,"passed_time":0.4173621958,"remaining_time":0.2668381252},
{"learn":[5.361656935],"iteration":61,"passed_time":0.4217001454,"remaining_time":0.2584613794},
{"learn":[5.333370795],"iteration":62,"passed_time":0.426000326,"remaining_time":0.2501906676},
{"learn":[5.310928709],"iteration":63,"passed_time":0.4284796576,"remaining_time":0.2410198074},
{"learn":[5.291533313],"iteration":64,"passed_time":0.4315163975,"remaining_time":0.2323549833},
{"learn":[5.268023439],"iteration":65,"passed_time":0.4356353668,"remaining_time":0.2244182193},
{"learn":[5.247061791],"iteration":66,"passed_time":0.4384196111,"remaining_time":0.2159380174},
{"learn":[5.221895362],"iteration":67,"passed_time":0.4426752343,"remaining_time":0.2083177573},
{"learn":[5.201103894],"iteration":68,"passed_time":0.446717702,"remaining_time":0.2006992574},
{"learn":[5.181132333],"iteration":69,"passed_time":0.4505180348,"remaining_time":0.1930791578},
{"learn":[5.167209818],"iteration":70,"passed_time":0.4527301003,"remaining_time":0.1849179283},
{"learn":[5.156700592],"iteration":71,"passed_time":0.4540955092,"remaining_time":0.176592698},
{"learn":[5.143000136],"iteration":72,"passed_time":0.4580493613,"remaining_time":0.1694155172},
{"learn":[5.123875105],"iteration":73,"passed_time":0.4621377362,"remaining_time":0.1623727181},
{"learn":[5.107102211],"iteration":74,"passed_time":0.4659947782,"remaining_time":0.1553315927},
{"learn":[5.088236153],"iteration":75,"passed_time":0.4697749756,"remaining_time":0.1483499923},
{"learn":[5.07696038],"iteration":76,"passed_time":0.473584017,"remaining_time":0.1414601609},
{"learn":[5.059420772],"iteration":77,"passed_time":0.4773489241,"remaining_time":0.134636876},
{"learn":[5.044663439],"iteration":78,"passed_time":0.4810770224,"remaining_time":0.1278812338},
{"learn":[5.034331109],"iteration":79,"passed_time":0.4847502063,"remaining_time":0.1211875516},
{"learn":[5.022379662],"iteration":80,"passed_time":0.4883902766,"remaining_time":0.1145606822},
{"learn":[5.006398181],"iteration":81,"passed_time":0.49237021,"remaining_time":0.1080812656},
{"learn":[4.98745025],"iteration":82,"passed_time":0.4966105834,"remaining_time":0.1017154207},
{"learn":[4.978030543],"iteration":83,"passed_time":0.5009919922,"remaining_time":0.09542704613},
{"learn":[4.968841194],"iteration":84,"passed_time":0.5051751851,"remaining_time":0.08914856207},
{"learn":[4.95391665],"iteration":85,"passed_time":0.5091248765,"remaining_time":0.08288079385},
{"learn":[4.941458054],"iteration":86,"passed_time":0.5139838036,"remaining_time":0.07680217755},
{"learn":[4.925203976],"iteration":87,"passed_time":0.5179853989,"remaining_time":0.07063437258},
{"learn":[4.91714823],"iteration":88,"passed_time":0.5226051517,"remaining_time":0.06459164797},
{"learn":[4.901671635],"iteration":89,"passed_time":0.5267056727,"remaining_time":0.05852285253},
{"learn":[4.894881364],"iteration":90,"passed_time":0.5284787811,"remaining_time":0.0522671322},
{"learn":[4.883116475],"iteration":91,"passed_time":0.5321658299,"remaining_time":0.04627528956},
{"learn":[4.872872464],"iteration":92,"passed_time":0.536163048,"remaining_time":0.04035635845},
{"learn":[4.866618861],"iteration":93,"passed_time":0.5403006956,"remaining_time":0.03448727844},
{"learn":[4.850654125],"iteration":94,"passed_time":0.5442780756,"remaining_time":0.0286462145},
{"learn":[4.839903099],"iteration":95,"passed_time":0.5481526005,"remaining_time":0.02283969169},
{"learn":[4.830527716],"iteration":96,"passed_time":0.553786905,"remaining_time":0.01712743005},
{"learn":[4.822498989],"iteration":97,"passed_time":0.5579862137,"remaining_time":0.01138747375},
{"learn":[4.81968811],"iteration":98,"passed_time":0.5594601995,"remaining_time":0.005651113126},
{"learn":[4.805321456],"iteration":99,"passed_time":0.5635881633,"remaining_time":0}
]}